MANIFEST.in
NEWS.txt
README.rst
setup.py
src/ttr/__init__.py
src/ttr.xml.csv2xml.egg-info/PKG-INFO
src/ttr.xml.csv2xml.egg-info/SOURCES.txt
src/ttr.xml.csv2xml.egg-info/dependency_links.txt
src/ttr.xml.csv2xml.egg-info/namespace_packages.txt
src/ttr.xml.csv2xml.egg-info/not-zip-safe
src/ttr.xml.csv2xml.egg-info/top_level.txt
src/ttr/xml/__init__.py
src/ttr/xml/csv2xml/__init__.py