Metadata-Version: 1.0
Name: ttr.xml.csv2xml
Version: 0.1.2dev002
Summary: module, providing conversion of csv file into xml
Home-page: https://bitbucket.org/vlcinsky/ttr.xml.csv2xml
Author: Jan Vlcinsky
Author-email: jan.vlcinsky@gmail.com
License: BSD
Keywords: xml csv module
Platform: UNKNOWN
Classifier: Development Status :: 3 - Alpha
Classifier: Intended Audience :: Developers
Classifier: License :: OSI Approved :: BSD License
Classifier: Programming Language :: Python :: 2.5
Classifier: Programming Language :: Python :: 2.6
Classifier: Programming Language :: Python :: 2.7
Classifier: Topic :: Text Processing :: Markup :: XML
